msa/__init__.py
msa/__main__.py
msa/command_line.py
msa/actions/__init__.py
msa/actions/add_action.py
msa/actions/delete_action.py
msa/actions/doctor_action.py
msa/actions/list_action.py
msa/actions/use_action.py
msa/model/__init__.py
msa/model/setting.py
msa/repositories/__init__.py
msa/repositories/setting_repository.py
msa/services/__init__.py
msa/services/file_service.py
msa/utils/__init__.py
msa/utils/config.py
msa/utils/log.py
msa-1.1.2.data/scripts/msa
test/__init__.py
test/file_service_test.py
msa-1.1.2.dist-info/LICENSE.md
msa-1.1.2.dist-info/METADATA
msa-1.1.2.dist-info/WHEEL
msa-1.1.2.dist-info/entry_points.txt
msa-1.1.2.dist-info/top_level.txt
msa-1.1.2.dist-info/RECORD
